{
  "v": "5.7.0",
  "fr": 30,
  "ip": 0,
  "op": 120,
  "w": 500,
  "h": 400,
  "nm": "City Lights HELIX",
  "assets": [],
  "slots": {
    "bgColor": { "p": { "a": 0, "k": [0, 0, 0, 0] } }
  },
  "layers": [
    {
      "ty": 4, "nm": "pulse-ring", "ip": 75, "op": 120, "st": 75,
      "ks": {
        "o": { "a": 1, "k": [
          { "t": 75, "s": [50], "i": { "x": [0.4], "y": [1] }, "o": { "x": [0.6], "y": [0] } },
          { "t": 118, "s": [0] }
        ]},
        "p": { "a": 0, "k": [250, 120, 0] },
        "a": { "a": 0, "k": [0, 0, 0] },
        "s": { "a": 1, "k": [
          { "t": 75, "s": [100, 100, 100], "i": { "x": [0.4, 0.4, 0.4], "y": [1, 1, 1] }, "o": { "x": [0.6, 0.6, 0.6], "y": [0, 0, 0] } },
          { "t": 118, "s": [600, 600, 100] }
        ]}
      },
      "shapes": [
        {
          "ty": "gr", "nm": "ring", "it": [
            { "ty": "el", "p": { "a": 0, "k": [0, 0] }, "s": { "a": 0, "k": [30, 30] } },
            { "ty": "st", "c": { "a": 0, "k": [0.0627, 0.7255, 0.5059, 1] }, "o": { "a": 0, "k": 100 }, "w": { "a": 0, "k": 2 } },
            { "ty": "tr", "p": { "a": 0, "k": [0, 0] }, "a": { "a": 0, "k": [0, 0] }, "s": { "a": 0, "k": [100, 100] }, "r": { "a": 0, "k": 0 }, "o": { "a": 0, "k": 100 } }
          ]
        }
      ]
    },
    {
      "ty": 4, "nm": "building-1", "ip": 0, "op": 120, "st": 0,
      "ks": { "o": { "a": 0, "k": 100 }, "p": { "a": 0, "k": [65, 310, 0] }, "a": { "a": 0, "k": [0, 0, 0] }, "s": { "a": 0, "k": [100, 100, 100] } },
      "shapes": [{ "ty": "gr", "nm": "b1", "it": [
        { "ty": "rc", "p": { "a": 0, "k": [0, 0] }, "s": { "a": 0, "k": [70, 180] }, "r": { "a": 0, "k": 4 } },
        { "ty": "fl", "c": { "a": 0, "k": [0.12, 0.22, 0.17, 1] }, "o": { "a": 0, "k": 100 } },
        { "ty": "tr", "p": { "a": 0, "k": [0, 0] }, "a": { "a": 0, "k": [0, 0] }, "s": { "a": 0, "k": [100, 100] }, "r": { "a": 0, "k": 0 }, "o": { "a": 0, "k": 100 } }
      ]}]
    },
    {
      "ty": 4, "nm": "building-2", "ip": 0, "op": 120, "st": 0,
      "ks": { "o": { "a": 0, "k": 100 }, "p": { "a": 0, "k": [155, 280, 0] }, "a": { "a": 0, "k": [0, 0, 0] }, "s": { "a": 0, "k": [100, 100, 100] } },
      "shapes": [{ "ty": "gr", "nm": "b2", "it": [
        { "ty": "rc", "p": { "a": 0, "k": [0, 0] }, "s": { "a": 0, "k": [80, 240] }, "r": { "a": 0, "k": 4 } },
        { "ty": "fl", "c": { "a": 0, "k": [0.08, 0.16, 0.12, 1] }, "o": { "a": 0, "k": 100 } },
        { "ty": "tr", "p": { "a": 0, "k": [0, 0] }, "a": { "a": 0, "k": [0, 0] }, "s": { "a": 0, "k": [100, 100] }, "r": { "a": 0, "k": 0 }, "o": { "a": 0, "k": 100 } }
      ]}]
    },
    {
      "ty": 4, "nm": "building-3-tallest", "ip": 0, "op": 120, "st": 0,
      "ks": { "o": { "a": 0, "k": 100 }, "p": { "a": 0, "k": [250, 250, 0] }, "a": { "a": 0, "k": [0, 0, 0] }, "s": { "a": 0, "k": [100, 100, 100] } },
      "shapes": [{ "ty": "gr", "nm": "b3", "it": [
        { "ty": "rc", "p": { "a": 0, "k": [0, 0] }, "s": { "a": 0, "k": [65, 300] }, "r": { "a": 0, "k": 4 } },
        { "ty": "fl", "c": { "a": 0, "k": [0.10, 0.20, 0.15, 1] }, "o": { "a": 0, "k": 100 } },
        { "ty": "tr", "p": { "a": 0, "k": [0, 0] }, "a": { "a": 0, "k": [0, 0] }, "s": { "a": 0, "k": [100, 100] }, "r": { "a": 0, "k": 0 }, "o": { "a": 0, "k": 100 } }
      ]}]
    },
    {
      "ty": 4, "nm": "building-4", "ip": 0, "op": 120, "st": 0,
      "ks": { "o": { "a": 0, "k": 100 }, "p": { "a": 0, "k": [340, 300, 0] }, "a": { "a": 0, "k": [0, 0, 0] }, "s": { "a": 0, "k": [100, 100, 100] } },
      "shapes": [{ "ty": "gr", "nm": "b4", "it": [
        { "ty": "rc", "p": { "a": 0, "k": [0, 0] }, "s": { "a": 0, "k": [75, 200] }, "r": { "a": 0, "k": 4 } },
        { "ty": "fl", "c": { "a": 0, "k": [0.12, 0.22, 0.17, 1] }, "o": { "a": 0, "k": 100 } },
        { "ty": "tr", "p": { "a": 0, "k": [0, 0] }, "a": { "a": 0, "k": [0, 0] }, "s": { "a": 0, "k": [100, 100] }, "r": { "a": 0, "k": 0 }, "o": { "a": 0, "k": 100 } }
      ]}]
    },
    {
      "ty": 4, "nm": "building-5", "ip": 0, "op": 120, "st": 0,
      "ks": { "o": { "a": 0, "k": 100 }, "p": { "a": 0, "k": [430, 325, 0] }, "a": { "a": 0, "k": [0, 0, 0] }, "s": { "a": 0, "k": [100, 100, 100] } },
      "shapes": [{ "ty": "gr", "nm": "b5", "it": [
        { "ty": "rc", "p": { "a": 0, "k": [0, 0] }, "s": { "a": 0, "k": [85, 150] }, "r": { "a": 0, "k": 4 } },
        { "ty": "fl", "c": { "a": 0, "k": [0.08, 0.16, 0.12, 1] }, "o": { "a": 0, "k": 100 } },
        { "ty": "tr", "p": { "a": 0, "k": [0, 0] }, "a": { "a": 0, "k": [0, 0] }, "s": { "a": 0, "k": [100, 100] }, "r": { "a": 0, "k": 0 }, "o": { "a": 0, "k": 100 } }
      ]}]
    },
    {
      "ty": 4, "nm": "windows", "ip": 0, "op": 120, "st": 0,
      "ks": { "o": { "a": 0, "k": 100 }, "p": { "a": 0, "k": [0, 0, 0] }, "a": { "a": 0, "k": [0, 0, 0] }, "s": { "a": 0, "k": [100, 100, 100] } },
      "shapes": [
        { "ty": "gr", "nm": "w1", "it": [
          { "ty": "rc", "p": { "a": 0, "k": [50, 370] }, "s": { "a": 0, "k": [10, 10] }, "r": { "a": 0, "k": 2 } },
          { "ty": "fl", "c": { "a": 0, "k": [0.0627, 0.7255, 0.5059, 1] }, "o": { "a": 1, "k": [{ "t": 0, "s": [10] }, { "t": 8, "s": [10] }, { "t": 10, "s": [100] }] } },
          { "ty": "tr", "p": { "a": 0, "k": [0, 0] }, "a": { "a": 0, "k": [0, 0] }, "s": { "a": 0, "k": [100, 100] }, "r": { "a": 0, "k": 0 }, "o": { "a": 0, "k": 100 } }
        ]},
        { "ty": "gr", "nm": "w2", "it": [
          { "ty": "rc", "p": { "a": 0, "k": [75, 370] }, "s": { "a": 0, "k": [10, 10] }, "r": { "a": 0, "k": 2 } },
          { "ty": "fl", "c": { "a": 0, "k": [0.0627, 0.7255, 0.5059, 1] }, "o": { "a": 1, "k": [{ "t": 0, "s": [10] }, { "t": 12, "s": [10] }, { "t": 14, "s": [100] }] } },
          { "ty": "tr", "p": { "a": 0, "k": [0, 0] }, "a": { "a": 0, "k": [0, 0] }, "s": { "a": 0, "k": [100, 100] }, "r": { "a": 0, "k": 0 }, "o": { "a": 0, "k": 100 } }
        ]},
        { "ty": "gr", "nm": "w3", "it": [
          { "ty": "rc", "p": { "a": 0, "k": [50, 345] }, "s": { "a": 0, "k": [10, 10] }, "r": { "a": 0, "k": 2 } },
          { "ty": "fl", "c": { "a": 0, "k": [0.2039, 0.8275, 0.6, 1] }, "o": { "a": 1, "k": [{ "t": 0, "s": [10] }, { "t": 16, "s": [10] }, { "t": 18, "s": [100] }] } },
          { "ty": "tr", "p": { "a": 0, "k": [0, 0] }, "a": { "a": 0, "k": [0, 0] }, "s": { "a": 0, "k": [100, 100] }, "r": { "a": 0, "k": 0 }, "o": { "a": 0, "k": 100 } }
        ]},
        { "ty": "gr", "nm": "w4", "it": [
          { "ty": "rc", "p": { "a": 0, "k": [75, 345] }, "s": { "a": 0, "k": [10, 10] }, "r": { "a": 0, "k": 2 } },
          { "ty": "fl", "c": { "a": 0, "k": [0.0627, 0.7255, 0.5059, 1] }, "o": { "a": 1, "k": [{ "t": 0, "s": [10] }, { "t": 20, "s": [10] }, { "t": 22, "s": [100] }] } },
          { "ty": "tr", "p": { "a": 0, "k": [0, 0] }, "a": { "a": 0, "k": [0, 0] }, "s": { "a": 0, "k": [100, 100] }, "r": { "a": 0, "k": 0 }, "o": { "a": 0, "k": 100 } }
        ]},
        { "ty": "gr", "nm": "w5", "it": [
          { "ty": "rc", "p": { "a": 0, "k": [140, 370] }, "s": { "a": 0, "k": [10, 10] }, "r": { "a": 0, "k": 2 } },
          { "ty": "fl", "c": { "a": 0, "k": [0.2039, 0.8275, 0.6, 1] }, "o": { "a": 1, "k": [{ "t": 0, "s": [10] }, { "t": 24, "s": [10] }, { "t": 26, "s": [100] }] } },
          { "ty": "tr", "p": { "a": 0, "k": [0, 0] }, "a": { "a": 0, "k": [0, 0] }, "s": { "a": 0, "k": [100, 100] }, "r": { "a": 0, "k": 0 }, "o": { "a": 0, "k": 100 } }
        ]},
        { "ty": "gr", "nm": "w6", "it": [
          { "ty": "rc", "p": { "a": 0, "k": [168, 370] }, "s": { "a": 0, "k": [10, 10] }, "r": { "a": 0, "k": 2 } },
          { "ty": "fl", "c": { "a": 0, "k": [0.0627, 0.7255, 0.5059, 1] }, "o": { "a": 1, "k": [{ "t": 0, "s": [10] }, { "t": 28, "s": [10] }, { "t": 30, "s": [100] }] } },
          { "ty": "tr", "p": { "a": 0, "k": [0, 0] }, "a": { "a": 0, "k": [0, 0] }, "s": { "a": 0, "k": [100, 100] }, "r": { "a": 0, "k": 0 }, "o": { "a": 0, "k": 100 } }
        ]},
        { "ty": "gr", "nm": "w7", "it": [
          { "ty": "rc", "p": { "a": 0, "k": [140, 340] }, "s": { "a": 0, "k": [10, 10] }, "r": { "a": 0, "k": 2 } },
          { "ty": "fl", "c": { "a": 0, "k": [0.0627, 0.7255, 0.5059, 1] }, "o": { "a": 1, "k": [{ "t": 0, "s": [10] }, { "t": 32, "s": [10] }, { "t": 34, "s": [100] }] } },
          { "ty": "tr", "p": { "a": 0, "k": [0, 0] }, "a": { "a": 0, "k": [0, 0] }, "s": { "a": 0, "k": [100, 100] }, "r": { "a": 0, "k": 0 }, "o": { "a": 0, "k": 100 } }
        ]},
        { "ty": "gr", "nm": "w8", "it": [
          { "ty": "rc", "p": { "a": 0, "k": [168, 340] }, "s": { "a": 0, "k": [10, 10] }, "r": { "a": 0, "k": 2 } },
          { "ty": "fl", "c": { "a": 0, "k": [0.2039, 0.8275, 0.6, 1] }, "o": { "a": 1, "k": [{ "t": 0, "s": [10] }, { "t": 34, "s": [10] }, { "t": 36, "s": [100] }] } },
          { "ty": "tr", "p": { "a": 0, "k": [0, 0] }, "a": { "a": 0, "k": [0, 0] }, "s": { "a": 0, "k": [100, 100] }, "r": { "a": 0, "k": 0 }, "o": { "a": 0, "k": 100 } }
        ]},
        { "ty": "gr", "nm": "w9", "it": [
          { "ty": "rc", "p": { "a": 0, "k": [237, 370] }, "s": { "a": 0, "k": [10, 10] }, "r": { "a": 0, "k": 2 } },
          { "ty": "fl", "c": { "a": 0, "k": [0.0627, 0.7255, 0.5059, 1] }, "o": { "a": 1, "k": [{ "t": 0, "s": [10] }, { "t": 36, "s": [10] }, { "t": 38, "s": [100] }] } },
          { "ty": "tr", "p": { "a": 0, "k": [0, 0] }, "a": { "a": 0, "k": [0, 0] }, "s": { "a": 0, "k": [100, 100] }, "r": { "a": 0, "k": 0 }, "o": { "a": 0, "k": 100 } }
        ]},
        { "ty": "gr", "nm": "w10", "it": [
          { "ty": "rc", "p": { "a": 0, "k": [260, 370] }, "s": { "a": 0, "k": [10, 10] }, "r": { "a": 0, "k": 2 } },
          { "ty": "fl", "c": { "a": 0, "k": [0.2039, 0.8275, 0.6, 1] }, "o": { "a": 1, "k": [{ "t": 0, "s": [10] }, { "t": 40, "s": [10] }, { "t": 42, "s": [100] }] } },
          { "ty": "tr", "p": { "a": 0, "k": [0, 0] }, "a": { "a": 0, "k": [0, 0] }, "s": { "a": 0, "k": [100, 100] }, "r": { "a": 0, "k": 0 }, "o": { "a": 0, "k": 100 } }
        ]},
        { "ty": "gr", "nm": "w11", "it": [
          { "ty": "rc", "p": { "a": 0, "k": [237, 340] }, "s": { "a": 0, "k": [10, 10] }, "r": { "a": 0, "k": 2 } },
          { "ty": "fl", "c": { "a": 0, "k": [0.0627, 0.7255, 0.5059, 1] }, "o": { "a": 1, "k": [{ "t": 0, "s": [10] }, { "t": 44, "s": [10] }, { "t": 46, "s": [100] }] } },
          { "ty": "tr", "p": { "a": 0, "k": [0, 0] }, "a": { "a": 0, "k": [0, 0] }, "s": { "a": 0, "k": [100, 100] }, "r": { "a": 0, "k": 0 }, "o": { "a": 0, "k": 100 } }
        ]},
        { "ty": "gr", "nm": "w12", "it": [
          { "ty": "rc", "p": { "a": 0, "k": [260, 340] }, "s": { "a": 0, "k": [10, 10] }, "r": { "a": 0, "k": 2 } },
          { "ty": "fl", "c": { "a": 0, "k": [0.2039, 0.8275, 0.6, 1] }, "o": { "a": 1, "k": [{ "t": 0, "s": [10] }, { "t": 48, "s": [10] }, { "t": 50, "s": [100] }] } },
          { "ty": "tr", "p": { "a": 0, "k": [0, 0] }, "a": { "a": 0, "k": [0, 0] }, "s": { "a": 0, "k": [100, 100] }, "r": { "a": 0, "k": 0 }, "o": { "a": 0, "k": 100 } }
        ]},
        { "ty": "gr", "nm": "w13", "it": [
          { "ty": "rc", "p": { "a": 0, "k": [237, 310] }, "s": { "a": 0, "k": [10, 10] }, "r": { "a": 0, "k": 2 } },
          { "ty": "fl", "c": { "a": 0, "k": [0.0627, 0.7255, 0.5059, 1] }, "o": { "a": 1, "k": [{ "t": 0, "s": [10] }, { "t": 52, "s": [10] }, { "t": 54, "s": [100] }] } },
          { "ty": "tr", "p": { "a": 0, "k": [0, 0] }, "a": { "a": 0, "k": [0, 0] }, "s": { "a": 0, "k": [100, 100] }, "r": { "a": 0, "k": 0 }, "o": { "a": 0, "k": 100 } }
        ]},
        { "ty": "gr", "nm": "w14", "it": [
          { "ty": "rc", "p": { "a": 0, "k": [260, 310] }, "s": { "a": 0, "k": [10, 10] }, "r": { "a": 0, "k": 2 } },
          { "ty": "fl", "c": { "a": 0, "k": [0.2039, 0.8275, 0.6, 1] }, "o": { "a": 1, "k": [{ "t": 0, "s": [10] }, { "t": 56, "s": [10] }, { "t": 58, "s": [100] }] } },
          { "ty": "tr", "p": { "a": 0, "k": [0, 0] }, "a": { "a": 0, "k": [0, 0] }, "s": { "a": 0, "k": [100, 100] }, "r": { "a": 0, "k": 0 }, "o": { "a": 0, "k": 100 } }
        ]},
        { "ty": "gr", "nm": "w15", "it": [
          { "ty": "rc", "p": { "a": 0, "k": [325, 370] }, "s": { "a": 0, "k": [10, 10] }, "r": { "a": 0, "k": 2 } },
          { "ty": "fl", "c": { "a": 0, "k": [0.0627, 0.7255, 0.5059, 1] }, "o": { "a": 1, "k": [{ "t": 0, "s": [10] }, { "t": 60, "s": [10] }, { "t": 62, "s": [100] }] } },
          { "ty": "tr", "p": { "a": 0, "k": [0, 0] }, "a": { "a": 0, "k": [0, 0] }, "s": { "a": 0, "k": [100, 100] }, "r": { "a": 0, "k": 0 }, "o": { "a": 0, "k": 100 } }
        ]},
        { "ty": "gr", "nm": "w16", "it": [
          { "ty": "rc", "p": { "a": 0, "k": [352, 370] }, "s": { "a": 0, "k": [10, 10] }, "r": { "a": 0, "k": 2 } },
          { "ty": "fl", "c": { "a": 0, "k": [0.2039, 0.8275, 0.6, 1] }, "o": { "a": 1, "k": [{ "t": 0, "s": [10] }, { "t": 64, "s": [10] }, { "t": 66, "s": [100] }] } },
          { "ty": "tr", "p": { "a": 0, "k": [0, 0] }, "a": { "a": 0, "k": [0, 0] }, "s": { "a": 0, "k": [100, 100] }, "r": { "a": 0, "k": 0 }, "o": { "a": 0, "k": 100 } }
        ]},
        { "ty": "gr", "nm": "w17", "it": [
          { "ty": "rc", "p": { "a": 0, "k": [415, 370] }, "s": { "a": 0, "k": [10, 10] }, "r": { "a": 0, "k": 2 } },
          { "ty": "fl", "c": { "a": 0, "k": [0.0627, 0.7255, 0.5059, 1] }, "o": { "a": 1, "k": [{ "t": 0, "s": [10] }, { "t": 68, "s": [10] }, { "t": 70, "s": [100] }] } },
          { "ty": "tr", "p": { "a": 0, "k": [0, 0] }, "a": { "a": 0, "k": [0, 0] }, "s": { "a": 0, "k": [100, 100] }, "r": { "a": 0, "k": 0 }, "o": { "a": 0, "k": 100 } }
        ]},
        { "ty": "gr", "nm": "w18", "it": [
          { "ty": "rc", "p": { "a": 0, "k": [445, 370] }, "s": { "a": 0, "k": [10, 10] }, "r": { "a": 0, "k": 2 } },
          { "ty": "fl", "c": { "a": 0, "k": [0.2039, 0.8275, 0.6, 1] }, "o": { "a": 1, "k": [{ "t": 0, "s": [10] }, { "t": 72, "s": [10] }, { "t": 74, "s": [100] }] } },
          { "ty": "tr", "p": { "a": 0, "k": [0, 0] }, "a": { "a": 0, "k": [0, 0] }, "s": { "a": 0, "k": [100, 100] }, "r": { "a": 0, "k": 0 }, "o": { "a": 0, "k": 100 } }
        ]}
      ]
    }
  ]
}
